{
 "table_uid": "T-POL-0001-1",
 "cells": [
  {
   "row_start": 0,
   "row_end": 0,
   "col_start": 0,
   "col_end": 0,
   "text": "FICO Band",
   "bbox": [
    88,
    159,
    240,
    208
   ],
   "is_header": true,
   "is_handwritten": false
  },
  {
   "row_start": 0,
   "row_end": 0,
   "col_start": 1,
   "col_end": 1,
   "text": "LTV <=80%",
   "bbox": [
    238,
    164,
    390,
    214
   ],
   "is_header": true,
   "is_handwritten": false
  },
  {
   "row_start": 0,
   "row_end": 0,
   "col_start": 2,
   "col_end": 2,
   "text": "LTV 81-90%",
   "bbox": [
    388,
    170,
    540,
    219
   ],
   "is_header": true,
   "is_handwritten": false
  },
  {
   "row_start": 0,
   "row_end": 0,
   "col_start": 3,
   "col_end": 3,
   "text": "LTV 91-100%",
   "bbox": [
    538,
    175,
    689,
    225
   ],
   "is_header": true,
   "is_handwritten": false
  },
  {
   "row_start": 0,
   "row_end": 0,
   "col_start": 4,
   "col_end": 4,
   "text": "LTV 101-110%",
   "bbox": [
    688,
    181,
    839,
    230
   ],
   "is_header": true,
   "is_handwritten": false
  },
  {
   "row_start": 0,
   "row_end": 0,
   "col_start": 5,
   "col_end": 5,
   "text": "LTV 111-120%",
   "bbox": [
    838,
    186,
    989,
    236
   ],
   "is_header": true,
   "is_handwritten": false
  },
  {
   "row_start": 4,
   "row_end": 4,
   "col_start": 0,
   "col_end": 0,
   "text": "700-739",
   "bbox": [
    87,
    203,
    238,
    252
   ],
   "is_header": false,
   "is_handwritten": false
  },
  {
   "row_start": 4,
   "row_end": 4,
   "col_start": 1,
   "col_end": 1,
   "text": "4.32%",
   "bbox": [
    236,
    208,
    388,
    258
   ],
   "is_header": false,
   "is_handwritten": false
  },
  {
   "row_start": 4,
   "row_end": 4,
   "col_start": 2,
   "col_end": 2,
   "text": "7.93%",
   "bbox": [
    386,
    214,
    538,
    263
   ],
   "is_header": false,
   "is_handwritten": false
  },
  {
   "row_start": 4,
   "row_end": 4,
   "col_start": 3,
   "col_end": 3,
   "text": "4.82%",
   "bbox": [
    536,
    219,
    688,
    269
   ],
   "is_header": false,
   "is_handwritten": false
  },
  {
   "row_start": 4,
   "row_end": 4,
   "col_start": 4,
   "col_end": 4,
   "text": "9.43%",
   "bbox": [
    686,
    225,
    838,
    274
   ],
   "is_header": false,
   "is_handwritten": false
  },
  {
   "row_start": 4,
   "row_end": 4,
   "col_start": 5,
   "col_end": 5,
   "text": "4.69%",
   "bbox": [
    836,
    230,
    988,
    280
   ],
   "is_header": false,
   "is_handwritten": false
  },
  {
   "row_start": 5,
   "row_end": 5,
   "col_start": 0,
   "col_end": 0,
   "text": "740-779",
   "bbox": [
    85,
    247,
    236,
    296
   ],
   "is_header": false,
   "is_handwritten": false
  },
  {
   "row_start": 5,
   "row_end": 5,
   "col_start": 1,
   "col_end": 1,
   "text": "13.08%",
   "bbox": [
    235,
    252,
    386,
    302
   ],
   "is_header": false,
   "is_handwritten": false
  },
  {
   "row_start": 5,
   "row_end": 5,
   "col_start": 2,
   "col_end": 2,
   "text": "4.44%",
   "bbox": [
    385,
    258,
    536,
    307
   ],
   "is_header": false,
   "is_handwritten": false
  },
  {
   "row_start": 5,
   "row_end": 5,
   "col_start": 3,
   "col_end": 3,
   "text": "11.32%",
   "bbox": [
    535,
    263,
    686,
    312
   ],
   "is_header": false,
   "is_handwritten": false
  },
  {
   "row_start": 5,
   "row_end": 5,
   "col_start": 4,
   "col_end": 4,
   "text": "10.78%",
   "bbox": [
    685,
    269,
    836,
    318
   ],
   "is_header": false,
   "is_handwritten": false
  },
  {
   "row_start": 5,
   "row_end": 5,
   "col_start": 5,
   "col_end": 5,
   "text": "5.32%",
   "bbox": [
    834,
    274,
    986,
    323
   ],
   "is_header": false,
   "is_handwritten": false
  },
  {
   "row_start": 6,
   "row_end": 6,
   "col_start": 0,
   "col_end": 0,
   "text": "780+",
   "bbox": [
    83,
    291,
    235,
    340
   ],
   "is_header": false,
   "is_handwritten": false
  },
  {
   "row_start": 6,
   "row_end": 6,
   "col_start": 1,
   "col_end": 1,
   "text": "4.22%",
   "bbox": [
    233,
    296,
    385,
    345
   ],
   "is_header": false,
   "is_handwritten": false
  },
  {
   "row_start": 6,
   "row_end": 6,
   "col_start": 2,
   "col_end": 2,
   "text": "12.18%",
   "bbox": [
    383,
    302,
    535,
    351
   ],
   "is_header": false,
   "is_handwritten": false
  },
  {
   "row_start": 6,
   "row_end": 6,
   "col_start": 3,
   "col_end": 3,
   "text": "6.64%",
   "bbox": [
    533,
    307,
    685,
    356
   ],
   "is_header": false,
   "is_handwritten": false
  },
  {
   "row_start": 6,
   "row_end": 6,
   "col_start": 4,
   "col_end": 4,
   "text": "10.15%",
   "bbox": [
    683,
    312,
    834,
    362
   ],
   "is_header": false,
   "is_handwritten": false
  },
  {
   "row_start": 6,
   "row_end": 6,
   "col_start": 5,
   "col_end": 5,
   "text": "5.21%",
   "bbox": [
    833,
    318,
    984,
    367
   ],
   "is_header": false,
   "is_handwritten": false
  }
 ]
}