{
 "table_uid": "T-APP-0038-1",
 "cells": [
  {
   "row_start": 0,
   "row_end": 0,
   "col_start": 0,
   "col_end": 0,
   "text": "VIN",
   "bbox": [
    79,
    509,
    261,
    569
   ],
   "is_header": true,
   "is_handwritten": false
  },
  {
   "row_start": 0,
   "row_end": 0,
   "col_start": 1,
   "col_end": 1,
   "text": "Make",
   "bbox": [
    259,
    526,
    372,
    580
   ],
   "is_header": true,
   "is_handwritten": false
  },
  {
   "row_start": 0,
   "row_end": 0,
   "col_start": 2,
   "col_end": 2,
   "text": "Model",
   "bbox": [
    369,
    537,
    493,
    591
   ],
   "is_header": true,
   "is_handwritten": false
  },
  {
   "row_start": 0,
   "row_end": 0,
   "col_start": 3,
   "col_end": 3,
   "text": "Year",
   "bbox": [
    489,
    548,
    564,
    598
   ],
   "is_header": true,
   "is_handwritten": false
  },
  {
   "row_start": 0,
   "row_end": 0,
   "col_start": 4,
   "col_end": 4,
   "text": "Fuel",
   "bbox": [
    560,
    555,
    655,
    607
   ],
   "is_header": true,
   "is_handwritten": false
  },
  {
   "row_start": 0,
   "row_end": 0,
   "col_start": 5,
   "col_end": 5,
   "text": "Cond",
   "bbox": [
    651,
    564,
    747,
    616
   ],
   "is_header": true,
   "is_handwritten": false
  },
  {
   "row_start": 0,
   "row_end": 0,
   "col_start": 6,
   "col_end": 6,
   "text": "Value ($)",
   "bbox": [
    743,
    573,
    871,
    628
   ],
   "is_header": true,
   "is_handwritten": false
  },
  {
   "row_start": 1,
   "row_end": 1,
   "col_start": 0,
   "col_end": 0,
   "text": "VIN69535AL",
   "bbox": [
    78,
    552,
    259,
    611
   ],
   "is_header": false,
   "is_handwritten": false
  },
  {
   "row_start": 1,
   "row_end": 1,
   "col_start": 1,
   "col_end": 1,
   "text": "Kia",
   "bbox": [
    256,
    569,
    369,
    622
   ],
   "is_header": false,
   "is_handwritten": false
  },
  {
   "row_start": 1,
   "row_end": 1,
   "col_start": 2,
   "col_end": 2,
   "text": "Corolla",
   "bbox": [
    366,
    580,
    489,
    634
   ],
   "is_header": false,
   "is_handwritten": false
  },
  {
   "row_start": 1,
   "row_end": 1,
   "col_start": 3,
   "col_end": 3,
   "text": "2022",
   "bbox": [
    486,
    591,
    560,
    641
   ],
   "is_header": false,
   "is_handwritten": false
  },
  {
   "row_start": 1,
   "row_end": 1,
   "col_start": 4,
   "col_end": 4,
   "text": "EV",
   "bbox": [
    556,
    598,
    651,
    650
   ],
   "is_header": false,
   "is_handwritten": false
  },
  {
   "row_start": 1,
   "row_end": 1,
   "col_start": 5,
   "col_end": 5,
   "text": "New",
   "bbox": [
    647,
    607,
    743,
    658
   ],
   "is_header": false,
   "is_handwritten": false
  },
  {
   "row_start": 1,
   "row_end": 1,
   "col_start": 6,
   "col_end": 6,
   "text": "20,000",
   "bbox": [
    738,
    616,
    865,
    670
   ],
   "is_header": false,
   "is_handwritten": false
  }
 ]
}